{
  "id": "2eb6f4dd-67c1-48f8-be7c-c9d266c20897",
  "name": "JabbarRoot",
  "projectRootPath": "/media/adnan/Projects/JabbarRoot",
  "brickContextIds": [
    "e798488e-11b7-4104-b0a3-20cdeb96fca2"
  ],
  "options": {
    "compilationCompressionLevel": "standard",
    "compilationIncludeProjectTree": true,
    "defaultBrickCompressionLevel": "standard",
    "defaultBrickIncludeProjectTree": false,
    "defaultBrickIncludeProjectTreeMaxDepth": 7,
    "projectIgnoreFiles": [],
    "projectIgnorePatterns": []
  },
  "metadata": {
    "createdAt": "2025-06-28T16:59:20.205Z",
    "updatedAt": "2025-06-28T16:59:30.104Z"
  }
}